setup.py
wherethedjeck/__init__.py
wherethedjeck/core.py
wherethedjeck.egg-info/PKG-INFO
wherethedjeck.egg-info/SOURCES.txt
wherethedjeck.egg-info/dependency_links.txt
wherethedjeck.egg-info/not-zip-safe
wherethedjeck.egg-info/top_level.txt
wherethedjeck/bin/wtd