Metadata-Version: 1.0
Name: wherethedjeck
Version: 0.1
Summary: Quickly find where the heck things are in Django framework
Home-page: https://github.com/ramonsaraiva/wherethedjeck
Author: Ramon Saraiva
Author-email: ramonsaraiva@gmail.com
License: MIT
Platform: UNKNOWN
